lyric/__init__.py
lyric_lang-0.0.1.dist-info/METADATA
lyric_lang-0.0.1.dist-info/WHEEL
lyric_lang-0.0.1.dist-info/entry_points.txt
lyric_lang-0.0.1.dist-info/top_level.txt
lyric_lang-0.0.1.dist-info/RECORD
