Metadata-Version: 2.4
Name: lyric-lang
Version: 0.0.1
Summary: Lyric programming language — coming soon from MiraNova Studios
Author-email: MiraNova Studios <aeonath4@gmail.com>
License: MIT
Project-URL: Homepage, http://miranova.studio/lyric.html
Project-URL: Repository, https://github.com/Aeonath4/lyric
Keywords: language,lyric,compiler,ai,miranova
Classifier: Development Status :: 1 - Planning
Classifier: Programming Language :: Python :: 3
Classifier: Intended Audience :: Developers
Classifier: Topic :: Software Development :: Compilers
Classifier: License :: OSI Approved :: MIT License
Requires-Python: >=3.8
